Metadata-Version: 2.1
Name: extended-maths
Version: 0.1.1
Summary: Mathmatical functions
Home-page: https://github.com/harsh204016/extended-maths
Author-email: harshgupta204016@gmail.com
License: UNKNOWN
Platform: UNKNOWN
